rasterarea/__init__.py
rasterarea/foliummap.py
rasterarea/ipyleafletmap.py
rasterarea/rasterarea.py
rasterarea-0.0.6.dist-info/LICENSE
rasterarea-0.0.6.dist-info/METADATA
rasterarea-0.0.6.dist-info/WHEEL
rasterarea-0.0.6.dist-info/dependency_links.txt
rasterarea-0.0.6.dist-info/top_level.txt
rasterarea-0.0.6.dist-info/RECORD
