Metadata-Version: 2.1
Name: rasterarea
Version: 0.0.6
Summary: This package provides a more accurate way to claculate the area of rasters.
Home-page: https://github.com/Feng96/rasterarea
Author: Yinan Feng
Author-email: 1041267458@qq.com
License: MIT license
Keywords: rasterarea
Classifier: Development Status :: 2 - Pre-Alpha
Classifier: Intended Audience :: Developers
Classifier: License :: OSI Approved :: MIT License
Classifier: Natural Language :: English
Classifier: Programming Language :: Python :: 3
Classifier: Programming Language :: Python :: 3.7
Classifier: Programming Language :: Python :: 3.8
Classifier: Programming Language :: Python :: 3.9
Classifier: Programming Language :: Python :: 3.10
Requires-Python: >=3.7
License-File: LICENSE
Requires-Dist: folium
Requires-Dist: ipyleaflet
Requires-Dist: ipywidgets
Requires-Dist: geopandas
Requires-Dist: httpx
Requires-Dist: rasterio
Requires-Dist: lidario
Requires-Dist: numpy
Requires-Dist: pandas
Requires-Dist: geojson
Requires-Dist: xyzservices
Requires-Dist: geemap
Requires-Dist: matplotlib
Requires-Dist: ipyfilechooser
Requires-Dist: netCDF4
Requires-Dist: traitlets
